common_lib/__init__.py
common_lib/http_client.py
infolab_common_lib-1.0.5.dist-info/METADATA
infolab_common_lib-1.0.5.dist-info/WHEEL
infolab_common_lib-1.0.5.dist-info/RECORD
